moisten_ew/__init__.py
moisten_ew/_base.py
moisten_ew/_dispersion.py
moisten_ew/_fft.py
moisten_ew/_filter.py
moisten_ew/_filter_area.py
moisten_ew-0.1.3.dist-info/licenses/LICENSE
moisten_ew-0.1.3.dist-info/METADATA
moisten_ew-0.1.3.dist-info/WHEEL
moisten_ew-0.1.3.dist-info/top_level.txt
moisten_ew-0.1.3.dist-info/RECORD
