Metadata-Version: 2.4
Name: moisten-ew
Version: 0.1.3
Summary: This is a part of the Moisten package, including calculations for the equatorial waves.
Author-email: Lilidream <ubuntullmx@hotmail.com>
Project-URL: Documentation, http://moisten.nightship.cn/ew
Project-URL: Repository, https://gitee.com/lilidream/moisten-ew
Keywords: atmosphere,equatorial waves,moisten,meteorology,geophysical fluid dynamics
Requires-Python: >=3.12
License-File: LICENSE
Requires-Dist: xarray>=2024.03.0
Requires-Dist: numpy>=2.1.0
Requires-Dist: pint>=0.24.1
Requires-Dist: scipy>=1.14.0
Requires-Dist: shapely>=2.0.4
Provides-Extra: dev
Requires-Dist: matplotlib; extra == "dev"
Requires-Dist: netcdf4; extra == "dev"
Dynamic: license-file
